TreasuryPy/__init__.py
TreasuryPy/tp.py
TreasuryPy-0.0.1.dist-info/LICENSE
TreasuryPy-0.0.1.dist-info/METADATA
TreasuryPy-0.0.1.dist-info/WHEEL
TreasuryPy-0.0.1.dist-info/top_level.txt
TreasuryPy-0.0.1.dist-info/RECORD
