Metadata-Version: 2.1
Name: TreasuryPy
Version: 0.0.1
Summary: Python Wrapper for using the US Fiscal Data API
Home-page: https://github.com/sarosnicholas1/US-FD-TreasurPy
Author: Nicholas Saros
Author-email: nicksaros07@gmail.com
Classifier: Programming Language :: Python :: 3
Classifier: License :: OSI Approved :: MIT License
Classifier: Operating System :: OS Independent
Requires-Python: >=3.7
License-File: LICENSE
